colvarsfinder/__init__.py
colvarsfinder/core.py
colvarsfinder/nn.py
colvarsfinder/utils.py
colvars_finder-0.1.14.dist-info/LICENSE
colvars_finder-0.1.14.dist-info/METADATA
colvars_finder-0.1.14.dist-info/WHEEL
colvars_finder-0.1.14.dist-info/top_level.txt
colvars_finder-0.1.14.dist-info/RECORD
