Metadata-Version: 2.1
Name: colvars-finder
Version: 0.1.14
Summary: Find collective variables (CVs) by training neural networks.
Home-page: https://github.com/zwpku/colvars-finder
Author: Wei Zhang
Author-email: wzhangpku@gmail.com
Project-URL: Bug Tracker, https://github.com/zwpku/colvars-finder/issues
Classifier: Programming Language :: Python :: 3
Classifier: License :: OSI Approved :: MIT License
Classifier: Operating System :: Unix
Requires-Python: >=3.7
License-File: LICENSE
Requires-Dist: torch (>=1.10.0)
Requires-Dist: mdanalysis (>=2.0.0)
Requires-Dist: numpy (>=1.20.3)
Requires-Dist: pandas (>=1.3.5)
